openapidocs/__init__.py
openapidocs/common.py
openapidocs/logs.py
openapidocs/main.py
openapidocs/v2.py
openapidocs/v3.py
openapidocs/commands/__init__.py
openapidocs/commands/docs.py
openapidocs/mk/__init__.py
openapidocs/mk/common.py
openapidocs/mk/contents.py
openapidocs/mk/generate.py
openapidocs/mk/jinja.py
openapidocs/mk/md.py
openapidocs/mk/texts.py
openapidocs/mk/v3/__init__.py
openapidocs/mk/v3/examples.py
openapidocs/mk/v3/views_markdown/README.md
openapidocs/mk/v3/views_markdown/__init__.py
openapidocs/mk/v3/views_markdown/layout.html
openapidocs/mk/v3/views_markdown/partial/components-parameters.html
openapidocs/mk/v3/views_markdown/partial/components-responses.html
openapidocs/mk/v3/views_markdown/partial/components-schemas.html
openapidocs/mk/v3/views_markdown/partial/components-security-schemes.html
openapidocs/mk/v3/views_markdown/partial/content-examples.html
openapidocs/mk/v3/views_markdown/partial/external-docs.html
openapidocs/mk/v3/views_markdown/partial/info.html
openapidocs/mk/v3/views_markdown/partial/path-items.html
openapidocs/mk/v3/views_markdown/partial/request-auth.html
openapidocs/mk/v3/views_markdown/partial/request-body.html
openapidocs/mk/v3/views_markdown/partial/request-parameters.html
openapidocs/mk/v3/views_markdown/partial/request-responses.html
openapidocs/mk/v3/views_markdown/partial/schema-repr.html
openapidocs/mk/v3/views_markdown/partial/servers.html
openapidocs/mk/v3/views_markdown/partial/tags.html
openapidocs/mk/v3/views_markdown/partial/type.html
openapidocs/mk/v3/views_mkdocs/README.md
openapidocs/mk/v3/views_mkdocs/__init__.py
openapidocs/mk/v3/views_mkdocs/layout.html
openapidocs/mk/v3/views_mkdocs/partial/components-parameters.html
openapidocs/mk/v3/views_mkdocs/partial/components-responses.html
openapidocs/mk/v3/views_mkdocs/partial/components-schemas.html
openapidocs/mk/v3/views_mkdocs/partial/components-security-schemes.html
openapidocs/mk/v3/views_mkdocs/partial/content-examples.html
essentials_openapi-1.1.1.dist-info/METADATA
essentials_openapi-1.1.1.dist-info/WHEEL
essentials_openapi-1.1.1.dist-info/entry_points.txt
essentials_openapi-1.1.1.dist-info/licenses/LICENSE
essentials_openapi-1.1.1.dist-info/RECORD
