Metadata-Version: 2.4
Name: essentials-openapi
Version: 1.1.1
Summary: Classes to generate OpenAPI Documentation v3 and v2, in JSON and YAML.
Project-URL: Homepage, https://github.com/Neoteroi/essentials-openapi
Project-URL: Bug Tracker, https://github.com/Neoteroi/essentials-openapi/issues
Author-email: Roberto Prevato <roberto.prevato@gmail.com>
License-File: LICENSE
Keywords: Markdown,api,docs,documentation,json,openapi,swagger,v2,v3,yaml
Classifier: Development Status :: 5 - Production/Stable
Classifier: License :: OSI Approved :: MIT License
Classifier: Operating System :: OS Independent
Classifier: Programming Language :: Python :: 3
Classifier: Programming Language :: Python :: 3.9
Classifier: Programming Language :: Python :: 3.10
Classifier: Programming Language :: Python :: 3.11
Classifier: Programming Language :: Python :: 3.12
Classifier: Programming Language :: Python :: 3.13
Requires-Python: >=3.8
Requires-Dist: essentials>=1.1.5
Requires-Dist: markupsafe>=3.0.0
Requires-Dist: pyyaml>=6
Provides-Extra: full
Requires-Dist: click~=8.1.3; extra == 'full'
Requires-Dist: httpx<1; extra == 'full'
Requires-Dist: jinja2~=3.1.2; extra == 'full'
Requires-Dist: rich~=12.6.0; extra == 'full'
